{"cameraMode":{"drawMode":0,"name":"Shaded","section":"Shading Mode"},"sceneLighting":true,"audioPlay":false,"sceneViewState":{"showFog":true,"showMaterialUpdate":false,"showSkybox":true,"showFlares":true,"showImageEffects":true,"showParticleSystems":true,"showVisualEffectGraphs":true,"m_FxEnabled":true},"in2DMode":false,"pivot":{"x":36.40146255493164,"y":9.628379821777344,"z":-13.773605346679688},"rotation":{"x":-0.08730015903711319,"y":-0.5163280963897705,"z":0.053005579859018329,"w":-0.8503011465072632},"size":23.570388793945314,"orthographic":false}